MANIFEST.in
authenticator_requirements.txt
ez_setup.py
setup.py
django_authenticator/__init__.py
django_authenticator/admin.py
django_authenticator/backends.py
django_authenticator/conf.py
django_authenticator/decorators.py
django_authenticator/default_settings.py
django_authenticator/forms.py
django_authenticator/middleware.py
django_authenticator/mimeparse.py
django_authenticator/models.py
django_authenticator/tests.py
django_authenticator/urls.py
django_authenticator/util.py
django_authenticator/views.py
django_authenticator.egg-info/PKG-INFO
django_authenticator.egg-info/SOURCES.txt
django_authenticator.egg-info/dependency_links.txt
django_authenticator.egg-info/requires.txt
django_authenticator.egg-info/top_level.txt
django_authenticator/migrations/0001_initial.py
django_authenticator/migrations/0002_make_multiple_openids_possible.py
django_authenticator/migrations/0003_fill_in_provider_names.py
django_authenticator/migrations/0004_auto__add_field_userassociation_last_used_timestamp__add_unique_useras.py
django_authenticator/migrations/0005_auto__del_externallogindata.py
django_authenticator/migrations/__init__.py