Metadata-Version: 1.0
Name: django-authenticator
Version: 0.1.5
Summary: authentication client for django
Home-page: UNKNOWN
Author: Evgeny.Fadeev
Author-email: evgeny.fadeev@gmail.com
License: GPLv3
Keywords: authentication,oauth,openid
Platform: UNKNOWN
Classifier: Development Status :: 2 - Pre-Alpha
